fluxloop/__init__.py
fluxloop/buffer.py
fluxloop/client.py
fluxloop/config.py
fluxloop/context.py
fluxloop/decorators.py
fluxloop/models.py
fluxloop/recording.py
fluxloop/serialization.py
fluxloop/storage.py
fluxloop/schemas/__init__.py
fluxloop/schemas/config.py
fluxloop/schemas/trace.py
fluxloop-0.1.6.dist-info/METADATA
fluxloop-0.1.6.dist-info/WHEEL
fluxloop-0.1.6.dist-info/top_level.txt
fluxloop-0.1.6.dist-info/RECORD
