Metadata-Version: 2.4
Name: fluxloop
Version: 0.1.6
Summary: FluxLoop SDK for agent instrumentation and tracing
Author-email: FluxLoop Team <team@fluxloop.dev>
License: Apache-2.0
Project-URL: Homepage, https://github.com/chuckgu/fluxloop
Project-URL: Documentation, https://docs.fluxloop.dev
Project-URL: Repository, https://github.com/chuckgu/fluxloop
Project-URL: Issues, https://github.com/chuckgu/fluxloop/issues
Classifier: Development Status :: 3 - Alpha
Classifier: Intended Audience :: Developers
Classifier: License :: OSI Approved :: Apache Software License
Classifier: Programming Language :: Python :: 3
Classifier: Programming Language :: Python :: 3.11
Classifier: Programming Language :: Python :: 3.12
Requires-Python: >=3.11
Requires-Dist: pydantic>=2.0
Requires-Dist: httpx>=0.24.0
Requires-Dist: python-dotenv>=1.0.0
Provides-Extra: dev
Requires-Dist: pytest>=7.0; extra == "dev"
Requires-Dist: pytest-asyncio>=0.21.0; extra == "dev"
Requires-Dist: pytest-cov>=4.0; extra == "dev"
Requires-Dist: pytest-mock>=3.14.0; extra == "dev"
Requires-Dist: pexpect>=4.9.0; extra == "dev"
Requires-Dist: ruff>=0.1.0; extra == "dev"
Requires-Dist: mypy>=1.0; extra == "dev"
Requires-Dist: black>=23.0; extra == "dev"
Provides-Extra: langchain
Requires-Dist: langchain>=0.1.0; extra == "langchain"
Provides-Extra: langgraph
Requires-Dist: langgraph>=0.0.20; extra == "langgraph"
